num7.py
num7-1.0.37.dist-info/licenses/LICENSE.txt
num7-1.0.37.dist-info/METADATA
num7-1.0.37.dist-info/WHEEL
num7-1.0.37.dist-info/top_level.txt
num7-1.0.37.dist-info/RECORD
