Metadata-Version: 2.4
Name: num7
Version: 1.0.37
Summary: Num - SUPREME PRECISION GENERAL PURPOSE ARITHMETIC-LOGIC DECIMAL CLASS
Home-page: https://github.com/giocip/num7
Author: giocip
Author-email: giocip7@gmail.com
Classifier: Programming Language :: Python :: 3.13
Classifier: License :: OSI Approved :: MIT License
Classifier: Operating System :: OS Independent
License-File: LICENSE.txt
Dynamic: author
Dynamic: author-email
Dynamic: classifier
Dynamic: description
Dynamic: description-content-type
Dynamic: home-page
Dynamic: license-file
Dynamic: summary
